LICENSE
expflow/__init__.py
expflow/expflow.py
expflow-0.2.0.dist-info/LICENSE
expflow-0.2.0.dist-info/WHEEL
expflow-0.2.0.dist-info/METADATA
expflow-0.2.0.dist-info/RECORD
