Metadata-Version: 2.1
Name: expflow
Version: 0.2.0
Summary: A Python library for controlling the flow of psychological experiments.
Home-page: https://github.com/sammosummo/expflow
License: MIT
Keywords: psychology,neuroscience
Author: Sam Mathias
Requires-Python: >=3.6,<4.0
Classifier: Development Status :: 3 - Alpha
Classifier: Intended Audience :: Developers
Classifier: License :: OSI Approved :: MIT License
Classifier: Operating System :: OS Independent
Classifier: Programming Language :: Python :: 3
Classifier: Programming Language :: Python :: 3.6
Classifier: Programming Language :: Python :: 3.7
Classifier: Programming Language :: Python :: 3.8
Classifier: Programming Language :: Python :: 3.9
Classifier: Programming Language :: Python :: 3.10
Classifier: Programming Language :: Python :: 3.11
Classifier: Programming Language :: Python :: 3
Classifier: Programming Language :: Python :: 3.10
Classifier: Programming Language :: Python :: 3.11
Classifier: Programming Language :: Python :: 3.6
Classifier: Programming Language :: Python :: 3.7
Classifier: Programming Language :: Python :: 3.8
Classifier: Programming Language :: Python :: 3.9
Classifier: Topic :: Software Development :: Libraries :: Python Modules
Requires-Dist: dataclasses_json (>=0.5.7,<0.6.0)
Requires-Dist: localnow (>=0.1.0,<0.2.0)
Requires-Dist: logmixin (>=0.1.4,<0.2.0)
Project-URL: Documentation, https://github.com/sammosummo/expflow
Project-URL: Repository, https://github.com/sammosummo/expflow
